{"type": "FeatureCollection", "properties": {"ResponseMetaData": {"SearchResponse": {"found": 12, "display": "multiple"}, "SearchRequest": {"request": "Gomel,administration", "skip": 0, "results": 500, "boundedBy": [[37.048427, 55.43644866], [38.175903, 56.04690174]]}}}, "features": [{"type": "Feature", "geometry": {"type": "Point", "coordinates": [31.011627, 52.423802]}, "properties": {"name": "Gomelsky Oblastnoy Ispolnitelny Komitet", "description": "Belarus, horad Homie\u013a, praspiekt Lienina, 2", "boundedBy": [[31.010616, 52.423183], [31.012664, 52.424435]], "CompanyMetaData": {"id": "1003697903", "name": "Gomelsky Oblastnoy Ispolnitelny Komitet", "address": "horad Homie\u013a, praspiekt Lienina, 2", "url": "http://www.gomel-region.by/", "Phones": [{"type": "phone", "formatted": "+375 23 233-45-05"}, {"type": "phone", "formatted": "+375 23 233-45-19"}, {"type": "phone", "formatted": "+375 23 233-45-03"}, {"type": "phone", "formatted": "+375 23 233-45-04"}, {"type": "phone", "formatted": "+375 23 233-45-32"}, {"type": "phone", "formatted": "+375 23 233-45-62"}, {"type": "phone", "formatted": "+375 23 233-75-04"}, {"type": "phone", "formatted": "+375 23 275-45-19"}, {"type": "phone", "formatted": "+375 23 275-45-29"}, {"type": "phone", "formatted": "+375 23 233-45-20"}, {"type": "phone", "formatted": "+375 23 233-43-07"}, {"type": "phone", "formatted": "+375 23 233-46-93"}, {"type": "phone", "formatted": "+375 23 275-45-34"}], "Categories": [{"class": "government", "name": "Government administration"}], "Hours": {"text": "Mon-Fri 8:30\u00a0AM\u20135:30\u00a0PM, break 1:00\u00a0PM\u20132:00\u00a0PM", "Availabilities": [{"Intervals": [{"from": "08:30:00", "to": "13:00:00"}, {"from": "14:00:00", "to": "17:30:00"}], "Monday": true, "Tuesday": true, "Wednesday": true, "Thursday": true, "Friday": true}]}}}}, {"type": "Feature", "geometry": {"type": "Point", "coordinates": [31.012236, 52.428341]}, "properties": {"name": "Gomelsky Gorodskoy Ispolnitelny Komitet", "description": "Belarus, horad Homie\u013a, Sialianskaja vulica, 13", "boundedBy": [[31.007751, 52.425802], [31.015961, 52.430821]], "CompanyMetaData": {"id": "1078522575", "name": "Gomelsky Gorodskoy Ispolnitelny Komitet", "address": "horad Homie\u013a, Sialianskaja vulica, 13", "url": "http://gomel.gov.by/", "Phones": [{"type": "phone", "formatted": "+375 23 275-52-92"}, {"type": "phone", "formatted": "+375 23 253-52-92"}], "Categories": [{"class": "government", "name": "Government administration"}], "Hours": {"text": "Mon-Fri 8:30\u00a0AM\u20135:30\u00a0PM, break 1:00\u00a0PM\u20132:00\u00a0PM", "Availabilities": [{"Intervals": [{"from": "08:30:00", "to": "13:00:00"}, {"from": "14:00:00", "to": "17:30:00"}], "Monday": true, "Tuesday": true, "Wednesday": true, "Thursday": true, "Friday": true}]}}}}, {"type": "Feature", "geometry": {"type": "Point", "coordinates": [31.028646, 52.394114]}, "properties": {"name": "Administratsiya Novobelitskogo rayona", "description": "Belarus, horad Homie\u013a, vulica I\u013ai\u010da, 49", "boundedBy": [[31.024585, 52.391571], [31.032796, 52.396594]], "CompanyMetaData": {"id": "1026179446", "name": "Administratsiya Novobelitskogo rayona", "address": "horad Homie\u013a, vulica I\u013ai\u010da, 49", "url": "http://novobel.gov.by/ru", "Phones": [{"type": "phone", "formatted": "+375 23 251-42-10"}], "Categories": [{"class": "government", "name": "Government administration"}, {"class": "government", "name": "Government ministries, services"}], "Hours": {"text": "Mon-Fri 8:30\u00a0AM\u20135:30\u00a0PM, break 1:00\u00a0PM\u20132:00\u00a0PM", "Availabilities": [{"Intervals": [{"from": "08:30:00", "to": "13:00:00"}, {"from": "14:00:00", "to": "17:30:00"}], "Monday": true, "Tuesday": true, "Wednesday": true, "Thursday": true, "Friday": true}]}}}}, {"type": "Feature", "geometry": {"type": "Point", "coordinates": [31.01057, 52.422129]}, "properties": {"name": "Komitet po Trudu, Zanyatosti i Sotsialnoy Zashchite Gomelskogo Oblispolkoma", "description": "Belarus, horad Homie\u013a, \u0437\u0430\u0432\u0443\u043b\u0430\u043a \u0421\u043f\u0430\u0440\u0442\u0430\u043a\u0430, 2\u0410", "boundedBy": [[31.006556, 52.419585], [31.014766, 52.424605]], "CompanyMetaData": {"id": "1089039561", "name": "Komitet po Trudu, Zanyatosti i Sotsialnoy Zashchite Gomelskogo Oblispolkoma", "address": "horad Homie\u013a, \u0437\u0430\u0432\u0443\u043b\u0430\u043a \u0421\u043f\u0430\u0440\u0442\u0430\u043a\u0430, 2\u0410", "url": "http://ktzsz-gomel.gov.by/", "Phones": [{"type": "phone", "formatted": "+375 23 250-91-74"}, {"type": "phone", "formatted": "+375 23 250-93-21"}, {"type": "phone", "formatted": "+375 23 275-06-08"}, {"type": "phone", "formatted": "+375 23 275-71-81"}, {"type": "phone", "formatted": "+375 23 250-93-64"}, {"type": "phone", "formatted": "+375 23 250-93-11"}, {"type": "phone", "formatted": "+375 23 250-91-71"}, {"type": "phone", "formatted": "+375 23 250-91-90"}, {"type": "phone", "formatted": "+375 23 250-93-25"}], "Categories": [{"class": "government", "name": "Human services department"}, {"class": "government", "name": "Government ministries, services"}, {"class": "government", "name": "Government administration"}], "Hours": {"text": "Mon-Fri 8:30\u00a0AM\u20135:30\u00a0PM, break 1:00\u00a0PM\u20132:00\u00a0PM", "Availabilities": [{"Intervals": [{"from": "08:30:00", "to": "13:00:00"}, {"from": "14:00:00", "to": "17:30:00"}], "Monday": true, "Tuesday": true, "Wednesday": true, "Thursday": true, "Friday": true}]}}}}, {"type": "Feature", "geometry": {"type": "Point", "coordinates": [31.029105, 52.390817]}, "properties": {"name": "Gomelsky Rayonny Ispolnitelny Komitet", "description": "Belarus, horad Homie\u013a, vulica I\u013ai\u010da, 51\u0410", "boundedBy": [[31.02807, 52.390186], [31.030119, 52.391439]], "CompanyMetaData": {"id": "1068298331", "name": "Gomelsky Rayonny Ispolnitelny Komitet", "address": "horad Homie\u013a, vulica I\u013ai\u010da, 51\u0410", "url": "http://gomelisp.gov.by/", "Phones": [{"type": "phone", "formatted": "+375 23 253-77-82"}, {"type": "phone", "formatted": "+375 23 253-56-74"}, {"type": "phone", "formatted": "+375 23 253-61-68"}, {"type": "phone", "formatted": "+375 23 253-49-65"}, {"type": "phone", "formatted": "+375 23 236-07-69"}, {"type": "phone", "formatted": "+375 23 236-23-65"}], "Categories": [{"class": "government", "name": "Government administration"}], "Hours": {"text": "Mon-Fri 8:30\u00a0AM\u20135:30\u00a0PM, break 1:00\u00a0PM\u20132:00\u00a0PM", "Availabilities": [{"Intervals": [{"from": "08:30:00", "to": "13:00:00"}, {"from": "14:00:00", "to": "17:30:00"}], "Monday": true, "Tuesday": true, "Wednesday": true, "Thursday": true, "Friday": true}]}}}}, {"type": "Feature", "geometry": {"type": "Point", "coordinates": [31.011639, 52.423808]}, "properties": {"name": "Komitet po Selskomu Khozyaystvu i Prodovolstviyu Gomelskogo Oblispolkoma", "description": "Belarus, horad Homie\u013a, praspiekt Lienina, 2", "boundedBy": [[31.010616, 52.423183], [31.012664, 52.424435]], "CompanyMetaData": {"id": "1073020846", "name": "Komitet po Selskomu Khozyaystvu i Prodovolstviyu Gomelskogo Oblispolkoma", "address": "horad Homie\u013a, praspiekt Lienina, 2", "url": "http://www.agro.gomel.by/", "Phones": [{"type": "phone", "formatted": "+375 23 233-10-26"}, {"type": "phone", "formatted": "+375 23 233-43-84"}, {"type": "phone", "formatted": "+375 23 275-10-24"}, {"type": "phone", "formatted": "+375 23 233-43-80"}, {"type": "phone", "formatted": "+375 23 223-00-37"}], "Categories": [{"class": "government", "name": "Government administration"}], "Hours": {"text": "Mon-Fri 8:30\u00a0AM\u20135:30\u00a0PM, break 1:00\u00a0PM\u20132:00\u00a0PM", "Availabilities": [{"Intervals": [{"from": "08:30:00", "to": "13:00:00"}, {"from": "14:00:00", "to": "17:30:00"}], "Monday": true, "Tuesday": true, "Wednesday": true, "Thursday": true, "Friday": true}]}}}}, {"type": "Feature", "geometry": {"type": "Point", "coordinates": [30.805404, 51.939339]}, "properties": {"name": "Loyevsky Rayonny Ispolnitelny Komitet", "description": "Belarus, haradski pasiolak Loje\u016d, vulica Lienina, 2", "boundedBy": [[30.801255, 51.936737], [30.809465, 51.941812]], "CompanyMetaData": {"id": "1030459624", "name": "Loyevsky Rayonny Ispolnitelny Komitet", "address": "Homie\u013askaja voblas\u0107, haradski pasiolak Loje\u016d, vulica Lienina, 2", "url": "http://loev.gov.by/", "Phones": [{"type": "phone", "formatted": "+375 23 474-22-10"}, {"type": "phone", "formatted": "+375 23 474-07-01"}, {"type": "phone", "formatted": "+375 23 474-02-37"}], "Categories": [{"class": "government", "name": "Government administration"}], "Hours": {"text": "Mon-Fri 8:30\u00a0AM\u20135:30\u00a0PM, break 1:00\u00a0PM\u20132:00\u00a0PM", "Availabilities": [{"Intervals": [{"from": "08:30:00", "to": "13:00:00"}, {"from": "14:00:00", "to": "17:30:00"}], "Monday": true, "Tuesday": true, "Wednesday": true, "Thursday": true, "Friday": true}]}}}}, {"type": "Feature", "geometry": {"type": "Point", "coordinates": [31.008476, 52.42506]}, "properties": {"name": "\u0410\u0434\u043c\u0438\u043d\u0438\u0441\u0442\u0440\u0430\u0446\u0438\u044f \u0437\u043e\u043d \u043e\u0442\u0447\u0443\u0436\u0434\u0435\u043d\u0438\u044f \u0438 \u043e\u0442\u0441\u0435\u043b\u0435\u043d\u0438\u044f", "description": "Belarus, horad Homie\u013a, praspiekt Lienina, 10", "boundedBy": [[31.004094, 52.422601], [31.012305, 52.42762]], "CompanyMetaData": {"id": "237162147156", "name": "\u0410\u0434\u043c\u0438\u043d\u0438\u0441\u0442\u0440\u0430\u0446\u0438\u044f \u0437\u043e\u043d \u043e\u0442\u0447\u0443\u0436\u0434\u0435\u043d\u0438\u044f \u0438 \u043e\u0442\u0441\u0435\u043b\u0435\u043d\u0438\u044f", "address": "horad Homie\u013a, praspiekt Lienina, 10", "url": "http://www.gomel-region.gov.by/", "Phones": [{"type": "phone", "formatted": "+375 23 229-37-12"}, {"type": "phone", "formatted": "+375 23 229-37-19"}], "Categories": [{"class": "government", "name": "Government administration"}], "Hours": {"text": "Mon-Fri 8:30\u00a0AM\u20135:30\u00a0PM, break 1:00\u00a0PM\u20132:00\u00a0PM", "Availabilities": [{"Intervals": [{"from": "08:30:00", "to": "13:00:00"}, {"from": "14:00:00", "to": "17:30:00"}], "Monday": true, "Tuesday": true, "Wednesday": true, "Thursday": true, "Friday": true}]}}}}, {"type": "Feature", "geometry": {"type": "Point", "coordinates": [31.000932, 52.443064]}, "properties": {"name": "Francisk Skorina Gomel State University", "description": "Belarus, horad Homie\u013a, Savieckaja vulica, 104", "boundedBy": [[30.996827, 52.440556], [31.005038, 52.445573]], "CompanyMetaData": {"id": "43968752955", "name": "Francisk Skorina Gomel State University", "address": "horad Homie\u013a, Savieckaja vulica, 104", "url": "http://gsu.by/", "Phones": [{"type": "phone", "formatted": "+375 23 251-00-73"}, {"type": "phone", "formatted": "+375 23 251-00-71"}], "Categories": [{"class": "college", "name": "University, college"}]}}}, {"type": "Feature", "geometry": {"type": "Point", "coordinates": [31.019325, 52.427855]}, "properties": {"name": "Gomel State Medical University, building \u2116 2", "description": "Belarus, horad Homie\u013a, vulica Bilieckaha, 11", "boundedBy": [[31.018306, 52.42723], [31.020354, 52.428482]], "CompanyMetaData": {"id": "174294607448", "name": "Gomel State Medical University, building \u2116 2", "address": "horad Homie\u013a, vulica Bilieckaha, 11", "url": "http://www.gsmu.by/", "Phones": [{"type": "phone", "formatted": "+375 23 255-83-86"}], "Categories": [{"class": "college", "name": "University, college"}], "Hours": {"text": "Mon-Fri 8:00\u00a0AM\u20136:00\u00a0PM", "Availabilities": [{"Intervals": [{"from": "08:00:00", "to": "18:00:00"}], "Monday": true, "Tuesday": true, "Wednesday": true, "Thursday": true, "Friday": true}]}}}}, {"type": "Feature", "geometry": {"type": "Point", "coordinates": [16.941418, 52.408391]}, "properties": {"name": "Administrator Najmu - Pozna\u0144", "description": "Wojew\u00f3dztwo wielkopolskie, Pozna\u0144, ulica Chwaliszewo, 72", "boundedBy": [[16.937312, 52.40588], [16.945523, 52.410901]], "CompanyMetaData": {"id": "81079021856", "name": "Administrator Najmu - Pozna\u0144", "address": "Wojew\u00f3dztwo wielkopolskie, Pozna\u0144, ulica Chwaliszewo, 72", "url": "https://administratornajmu.pl/", "Phones": [{"type": "phone", "formatted": "+48  533 58 05 80"}], "Categories": [{"class": "government", "name": "Municipal housing authority"}]}}}, {"type": "Feature", "geometry": {"type": "Point", "coordinates": [19.457096, 51.764398]}, "properties": {"name": "Administrator \u0141\u00f3d\u017a", "description": "Wojew\u00f3dztwo \u0142\u00f3dzkie, \u0141\u00f3d\u017a, ulica Piotrkowska, 107", "boundedBy": [[19.452991, 51.76185], [19.461201, 51.766945]], "CompanyMetaData": {"id": "225408316709", "name": "Administrator \u0141\u00f3d\u017a", "address": "Wojew\u00f3dztwo \u0142\u00f3dzkie, \u0141\u00f3d\u017a, ulica Piotrkowska, 107", "url": "https://administratorlodz.pl/", "Phones": [{"type": "phone", "formatted": "+48  536 95 41 23"}], "Categories": [{"class": "government", "name": "Municipal housing authority"}]}}}]}