{"type": "FeatureCollection", "properties": {"ResponseMetaData": {"SearchResponse": {"found": 18, "display": "multiple"}, "SearchRequest": {"request": "Grodno,hotel", "skip": 0, "results": 500, "boundedBy": [[37.048427, 55.43644866], [38.175903, 56.04690174]]}}}, "features": [{"type": "Feature", "geometry": {"type": "Point", "coordinates": [23.985898, 53.658293]}, "properties": {"name": "Zoo_hotel_grodno", "description": "Belarus, \u0432\u0451\u0441\u043a\u0430 \u0413\u0440\u044b\u043d\u0451\u045e\u043a\u0430, 42", "boundedBy": [[23.981793, 53.655854], [23.990004, 53.660731]], "CompanyMetaData": {"id": "57001236509", "name": "Zoo_hotel_grodno", "address": "Hrodzienski rajon, \u0412\u0435\u0440\u0446\u044f\u043b\u0456\u0448\u043a\u0430\u045e\u0441\u043a\u0456 \u0441\u0435\u043b\u044c\u0441\u0430\u0432\u0435\u0442, \u0432\u0451\u0441\u043a\u0430 \u0413\u0440\u044b\u043d\u0451\u045e\u043a\u0430, 42", "Phones": [{"type": "phone", "formatted": "+375 29 788-61-63"}, {"type": "phone", "formatted": "+375 33 624-77-59"}], "Categories": [{"class": "petshop", "name": "Pet hotel"}], "Hours": {"text": "daily, 24 hours", "Availabilities": [{"TwentyFourHours": true, "Everyday": true}]}}}}, {"type": "Feature", "geometry": {"type": "Point", "coordinates": [23.832272, 53.680009]}, "properties": {"name": "Vs Design Hotel", "description": "Belarus, Hrodna, vulica Uryckaha, 23", "boundedBy": [[23.828208, 53.677588], [23.836419, 53.682463]], "CompanyMetaData": {"id": "55779203718", "name": "Vs Design Hotel", "address": "Hrodna, vulica Uryckaha, 23", "url": "https://www.vsdhotel.by/", "Phones": [{"type": "phone", "formatted": "+375 29 399-78-88"}, {"type": "phone", "formatted": "+375 33 624-56-39"}], "Categories": [{"class": "hotels", "name": "Hotel"}], "Hours": {"text": "daily, 24 hours", "Availabilities": [{"TwentyFourHours": true, "Everyday": true}]}}}}, {"type": "Feature", "geometry": {"type": "Point", "coordinates": [23.787371, 53.680491]}, "properties": {"name": "Kronon Park Hotel", "description": "Belarus, Hrodna, uro\u010dy\u0161\u010da Py\u0161ki, ulitsa Pyshki, 19", "boundedBy": [[23.783409, 53.678127], [23.79162, 53.683002]], "CompanyMetaData": {"id": "1104113664", "name": "Kronon Park Hotel", "address": "Hrodna, uro\u010dy\u0161\u010da Py\u0161ki, ulitsa Pyshki, 19", "url": "http://www.kronon.by/", "Phones": [{"type": "phone", "formatted": "+375 29 360-00-50"}, {"type": "phone", "formatted": "+375 15 273-98-00"}], "Categories": [{"class": "hotels", "name": "Hotel"}], "Hours": {"text": "daily, 24 hours", "Availabilities": [{"TwentyFourHours": true, "Everyday": true}]}}}}, {"type": "Feature", "geometry": {"type": "Point", "coordinates": [23.830279, 53.676671]}, "properties": {"name": "\u041d\u0435\u043c\u0430\u043d", "description": "Belarus, Hrodna, vulica Stefana Batoryja, 8", "boundedBy": [[23.826124, 53.674164], [23.834335, 53.679039]], "CompanyMetaData": {"id": "179019294254", "name": "\u041d\u0435\u043c\u0430\u043d", "address": "Hrodna, vulica Stefana Batoryja, 8", "url": "http://www.hotel-neman.by/", "Phones": [{"type": "phone", "formatted": "+375 15 279-17-00"}, {"type": "phone", "formatted": "+375 33 399-17-00"}, {"type": "phone_fax", "formatted": "+375 15 273-01-04"}, {"type": "phone", "formatted": "+375 44 791-81-79"}], "Categories": [{"class": "hotels", "name": "Hotel"}], "Hours": {"text": "daily, 24 hours", "Availabilities": [{"TwentyFourHours": true, "Everyday": true}]}}}}, {"type": "Feature", "geometry": {"type": "Point", "coordinates": [23.841785, 53.675449]}, "properties": {"name": "Semashko Hotel", "description": "Belarus, Hrodna, vulica Antonava, 10", "boundedBy": [[23.837676, 53.672932], [23.845887, 53.677807]], "CompanyMetaData": {"id": "1087934231", "name": "Semashko Hotel", "address": "Hrodna, vulica Antonava, 10", "url": "https://hotel-semashko.ru/", "Phones": [{"type": "phone", "formatted": "+375 15 262-45-31"}, {"type": "phone", "formatted": "+375 29 585-02-99"}, {"type": "phone", "formatted": "+375 33 640-46-55"}, {"type": "phone", "formatted": "+375 29 675-02-95"}, {"type": "phone", "formatted": "+375 29 637-28-44"}, {"type": "phone", "formatted": "+375 15 262-45-30"}, {"type": "phone", "formatted": "+375 15 275-02-95"}, {"type": "fax", "formatted": "+375 15 275-02-80"}], "Categories": [{"class": "hotels", "name": "Hotel"}], "Hours": {"text": "daily, 24 hours", "Availabilities": [{"TwentyFourHours": true, "Everyday": true}]}}}}, {"type": "Feature", "geometry": {"type": "Point", "coordinates": [19.02329, 50.275436]}, "properties": {"name": "Grodno II SP z o o", "description": "Poland, Silesia Province, Katowice, Al Korfantego 79 A", "boundedBy": [[19.013526, 50.264649], [19.025312, 50.29323]], "CompanyMetaData": {"id": "67174071545", "name": "Grodno II SP z o o", "address": "Poland, Silesia Province, Katowice, Al Korfantego 79 A", "Categories": [{"class": "hotels", "name": "Hotel"}]}}}, {"type": "Feature", "geometry": {"type": "Point", "coordinates": [23.846947, 53.654402]}, "properties": {"name": "Turist", "description": "Belarus, Hrodna, praspiekt Janki Kupaly, 63", "boundedBy": [[23.842554, 53.651969], [23.850765, 53.656846]], "CompanyMetaData": {"id": "1217388327", "name": "Turist", "address": "Hrodna, praspiekt Janki Kupaly, 63", "url": "http://grodnotourist.by/", "Phones": [{"type": "phone", "formatted": "+375 44 786-08-77"}, {"type": "phone", "formatted": "+375 15 239-24-40"}, {"type": "phone", "formatted": "+375 15 239-27-30"}, {"type": "phone", "formatted": "+375 15 239-26-30"}, {"type": "fax", "formatted": "+375 15 239-24-41"}], "Categories": [{"class": "hotels", "name": "Hotel"}], "Hours": {"text": "daily, 24 hours", "Availabilities": [{"TwentyFourHours": true, "Everyday": true}]}}}}, {"type": "Feature", "geometry": {"type": "Point", "coordinates": [23.833643, 53.679777]}, "properties": {"name": "Hello Grodno", "description": "Belarus, Hrodna, Haradni\u010danskaja vulica, 30", "boundedBy": [[23.829663, 53.67737], [23.837874, 53.682244]], "CompanyMetaData": {"id": "193576070314", "name": "Hello Grodno", "address": "Hrodna, Haradni\u010danskaja vulica, 30", "url": "https://hello-grodno-hostel.business.site/", "Phones": [{"type": "phone", "formatted": "+375 29 932-97-90"}, {"type": "phone", "formatted": "+375 29 787-94-26"}], "Categories": [{"class": "hotels", "name": "Hostel"}], "Hours": {"text": "daily, 2:00\u00a0PM\u201310:00\u00a0PM", "Availabilities": [{"Intervals": [{"from": "14:00:00", "to": "22:00:00"}], "Everyday": true}]}}}}, {"type": "Feature", "geometry": {"type": "Point", "coordinates": [23.83612, 53.6814]}, "properties": {"name": "Apartment in Grodno Grodno", "description": "Belarus, Grodno, Proletarskaya Ulitsa D.6, Kv.53", "boundedBy": [[23.834559, 53.680207], [23.842626, 53.681578]], "CompanyMetaData": {"id": "72548275381", "name": "Apartment in Grodno Grodno", "address": "Belarus, Grodno, Proletarskaya Ulitsa D.6, Kv.53", "Categories": [{"class": "hotels", "name": "Short-term housing rental"}, {"class": "hotels", "name": "Hotel"}]}}}, {"type": "Feature", "geometry": {"type": "Point", "coordinates": [23.838266, 53.682447]}, "properties": {"name": "Omega gostinitsa Oupp institut Grodnograzhdanproyekt", "description": "Belarus, Hrodna, vulica Michasia Vasi\u013aka, 40", "boundedBy": [[23.833993, 53.680052], [23.842204, 53.684927]], "CompanyMetaData": {"id": "1134411816", "name": "Omega gostinitsa Oupp institut Grodnograzhdanproyekt", "address": "Hrodna, vulica Michasia Vasi\u013aka, 40", "url": "https://www.hotel-omega.by/", "Phones": [{"type": "phone", "formatted": "+375 33 399-31-00"}, {"type": "phone", "formatted": "+375 15 262-32-65"}, {"type": "phone", "formatted": "+375 15 262-32-60"}], "Categories": [{"class": "hotels", "name": "Hotel"}], "Hours": {"text": "daily, 24 hours", "Availabilities": [{"TwentyFourHours": true, "Everyday": true}]}}}}, {"type": "Feature", "geometry": {"type": "Point", "coordinates": [23.736166, 53.626953]}, "properties": {"name": "Guest house Bread Salt", "description": "\u0411\u0435\u043b\u0430\u0440\u0443\u0441\u044c, \u0434\u0435\u0440\u0435\u0432\u043d\u044f \u041a\u043e\u0440\u043e\u0431\u0447\u0438\u0446\u044b, \u041e\u043a\u043e\u043b\u0438\u0447\u043d\u0430\u044f \u0443\u043b\u0438\u0446\u0430, 50", "boundedBy": [[23.732097, 53.624539], [23.740308, 53.62942]], "CompanyMetaData": {"id": "1705477560", "name": "Guest house Bread Salt", "address": "\u0413\u0440\u043e\u0434\u043d\u0435\u043d\u0441\u043a\u0438\u0439 \u0440\u0430\u0439\u043e\u043d, \u041a\u043e\u043f\u0442\u0451\u0432\u0441\u043a\u0438\u0439 \u0441\u0435\u043b\u044c\u0441\u043e\u0432\u0435\u0442, \u0434\u0435\u0440\u0435\u0432\u043d\u044f \u041a\u043e\u0440\u043e\u0431\u0447\u0438\u0446\u044b, \u041e\u043a\u043e\u043b\u0438\u0447\u043d\u0430\u044f \u0443\u043b\u0438\u0446\u0430, 50", "url": "https://guest-house-with-sauna.business.site/", "Phones": [{"type": "phone", "formatted": "+375 29 788-22-74"}], "Categories": [{"class": "hotels", "name": "Hotel"}], "Hours": {"text": "daily, 24 hours", "Availabilities": [{"TwentyFourHours": true, "Everyday": true}]}}}}, {"type": "Feature", "geometry": {"type": "Point", "coordinates": [23.8141, 53.67287]}, "properties": {"name": "Apartments Gagarina Grodno", "description": "Belarus, Grodno, Ul Gagarina 18B 118", "boundedBy": [[23.8077, 53.667315], [23.823968, 53.673508]], "CompanyMetaData": {"id": "97460905369", "name": "Apartments Gagarina Grodno", "address": "Belarus, Grodno, Ul Gagarina 18B 118", "Categories": [{"class": "hotels", "name": "Hotel"}]}}}, {"type": "Feature", "geometry": {"type": "Point", "coordinates": [23.773978, 53.695424]}, "properties": {"name": "Prival", "description": "Hrodzienski rajon, \u041f\u0430\u0434\u043b\u0430\u0431\u0435\u043d\u0441\u043a\u0456 \u0441\u0435\u043b\u044c\u0441\u0430\u0432\u0435\u0442, vioska Py\u0161ki", "boundedBy": [[23.51157, 53.371419], [24.457226, 53.970121]], "CompanyMetaData": {"id": "1675135208", "name": "Prival", "address": "Hrodzienski rajon, \u041f\u0430\u0434\u043b\u0430\u0431\u0435\u043d\u0441\u043a\u0456 \u0441\u0435\u043b\u044c\u0441\u0430\u0432\u0435\u0442, vioska Py\u0161ki", "url": "http://gtfprival.by/", "Phones": [{"type": "phone", "formatted": "+375 29 837-43-74"}], "Categories": [{"class": "travel agency", "name": "Resort"}], "Hours": {"text": "daily, 24 hours", "Availabilities": [{"TwentyFourHours": true, "Everyday": true}]}}}}, {"type": "Feature", "geometry": {"type": "Point", "coordinates": [23.830515, 53.676947]}, "properties": {"name": "\u041d\u0435\u043c\u0430\u043d", "description": "Belarus, Hrodna, vulica Stefana Batoryja, 8", "boundedBy": [[23.826124, 53.674164], [23.834335, 53.679039]], "CompanyMetaData": {"id": "46889589546", "name": "\u041d\u0435\u043c\u0430\u043d", "address": "Hrodna, vulica Stefana Batoryja, 8", "url": "http://www.hotel-neman.by/", "Phones": [{"type": "phone", "formatted": "+375 15 279-17-33"}, {"type": "phone", "formatted": "+375 29 159-17-48"}, {"type": "phone", "formatted": "+375 29 119-17-33"}, {"type": "phone", "formatted": "+375 15 279-17-48"}, {"type": "phone", "formatted": "+375 29 279-17-33"}, {"type": "phone", "formatted": "+375 44 791-81-79"}], "Categories": [{"class": "bars", "name": "Pub, bar"}, {"class": "restaurants", "name": "Restaurant"}], "Hours": {"text": "Mon-Thu 12:00\u00a0PM\u201312:00\u00a0AM; Fri,Sat 12:00\u00a0PM\u20132:00\u00a0AM; Sun 12:00\u00a0PM\u201312:00\u00a0AM", "Availabilities": [{"Intervals": [{"from": "12:00:00", "to": "00:00:00"}], "Monday": true, "Tuesday": true, "Wednesday": true, "Thursday": true}, {"Intervals": [{"from": "12:00:00", "to": "02:00:00"}], "Friday": true, "Saturday": true}, {"Intervals": [{"from": "12:00:00", "to": "00:00:00"}], "Sunday": true}]}}}}, {"type": "Feature", "geometry": {"type": "Point", "coordinates": [23.811767, 53.680217]}, "properties": {"name": "\u0423\u0441\u0430\u0434\u044c\u0431\u0430 \u043d\u0430 \u041d\u0435\u043c\u0430\u043d\u0441\u043a\u043e\u0439", "description": "\u0411\u0435\u043b\u0430\u0440\u0443\u0441\u044c, \u0413\u0440\u043e\u0434\u043d\u043e, \u041d\u0435\u043c\u0430\u043d\u0441\u043a\u0430\u044f \u0443\u043b\u0438\u0446\u0430, 52", "boundedBy": [[23.807628, 53.677738], [23.815838, 53.682612]], "CompanyMetaData": {"id": "97368196207", "name": "\u0423\u0441\u0430\u0434\u044c\u0431\u0430 \u043d\u0430 \u041d\u0435\u043c\u0430\u043d\u0441\u043a\u043e\u0439", "address": "\u0413\u0440\u043e\u0434\u043d\u043e, \u041d\u0435\u043c\u0430\u043d\u0441\u043a\u0430\u044f \u0443\u043b\u0438\u0446\u0430, 52", "url": "http://nanemanskoj.by/", "Phones": [{"type": "phone", "formatted": "+375 29 366-66-47"}, {"type": "phone", "formatted": "+375 29 780-24-30"}], "Categories": [{"class": "hotels", "name": "Hotel"}, {"class": "hotels", "name": "Short-term housing rental"}, {"class": "fallback services", "name": "Rental of venues for cultural events"}, {"class": "spa", "name": "Bathhouse"}, {"class": "office service", "name": "Real estate agency"}, {"class": "travel agency", "name": "Resort"}, {"class": "spa", "name": "Sauna"}], "Hours": {"text": "daily, 24 hours", "Availabilities": [{"TwentyFourHours": true, "Everyday": true}]}}}}, {"type": "Feature", "geometry": {"type": "Point", "coordinates": [24.394925, 53.149093]}, "properties": {"name": "Motel Skazka Grodno", "description": "\u0411\u0435\u043b\u0430\u0440\u0443\u0441\u044c, \u0412\u043e\u043b\u043a\u043e\u0432\u044b\u0441\u043a, \u0443\u043b\u0438\u0446\u0430 \u0422\u0438\u0442\u043e\u0432\u0430, 13", "boundedBy": [[24.390805, 53.146656], [24.399016, 53.151592]], "CompanyMetaData": {"id": "78122470974", "name": "Motel Skazka Grodno", "address": "Belarus, Hrodna Region, 13 Titova Str", "Categories": [{"class": "hotels", "name": "Hotel"}]}}}, {"type": "Feature", "geometry": {"type": "Point", "coordinates": [24.20912, 53.75246]}, "properties": {"name": "Suncamper 30 Grodno", "description": "Belarus, Grodno, Ozernyi Sanatorium", "boundedBy": [[24.187346, 53.734794], [24.21319, 53.779043]], "CompanyMetaData": {"id": "228730326271", "name": "Suncamper 30 Grodno", "address": "Belarus, Grodno, Ozernyi Sanatorium", "Categories": [{"class": "hotels", "name": "Hotel"}]}}}, {"type": "Feature", "geometry": {"type": "Point", "coordinates": [23.936912, 53.646639]}, "properties": {"name": "\u041f\u0440\u0438\u0433\u043e\u0434\u0438\u0447\u0438", "description": "Hrodzienski rajon, Putry\u0161ka\u016dski sie\u013asaviet, Village of Pryhodzichy", "boundedBy": [[23.51157, 53.371419], [24.457226, 53.970121]], "CompanyMetaData": {"id": "136402715030", "name": "\u041f\u0440\u0438\u0433\u043e\u0434\u0438\u0447\u0438", "address": "Hrodzienski rajon, Putry\u0161ka\u016dski sie\u013asaviet, Village of Pryhodzichy", "Phones": [{"type": "phone", "formatted": "+375 33 344-47-72"}], "Categories": [{"class": "travel agency", "name": "Resort"}], "Hours": {"text": "daily, 24 hours", "Availabilities": [{"TwentyFourHours": true, "Everyday": true}]}}}}]}